{
    "page": "lesson",
    "lessons": [
        {
            "title": "മുസ്ലിം ആവാനുള്ള അടിസ്ഥാനം: ശഹാദത്ത് (വിശ്വാസ പ്രഖ്യാപനം)",
            "desc": "",
            "active": true,
            "points": [
                {
                    "title": "ശഹാദത്തിൻ്റെ പദങ്ങൾ",
                    "desc": [
                        "ഇസ്‌ലാമിലേക്ക് പ്രവേശിക്കുന്നതിൻ്റെ ഏറ്റവും പ്രധാനപ്പെട്ടതും നിർബന്ധവുമായ അടിസ്ഥാനമാണിത്. ഇത് ഹൃദയം കൊണ്ട് വിശ്വസിച്ച് നാവുകൊണ്ട് പറയണം.",
                        "അശ്ഹദു അൻ ലാ ഇലാഹ ഇല്ലല്ലാഹ്, വ അശ്ഹദു അന്ന മുഹമ്മദൻ റസൂലുല്ലാഹ്.",
                        "അർത്ഥം: അല്ലാഹുവല്ലാതെ ആരാധനക്കർഹനായി മറ്റാരുമില്ലെന്ന് ഞാൻ സാക്ഷ്യം വഹിക്കുന്നു, മുഹമ്മദ് ﷺ അല്ലാഹുവിൻ്റെ ദൂതനാണെന്നും ഞാൻ സാക്ഷ്യം വഹിക്കുന്നു."
                    ],
                    "ref": [
                        {
                            "title": "ഇസ്‌ലാം കാര്യങ്ങൾ അഞ്ചാകുന്നു: അല്ലാഹുവല്ലാതെ ആരാധ്യനില്ലെന്നും മുഹമ്മദ് ﷺ അല്ലാഹുവിൻ്റെ ദൂതനാണെന്നും സാക്ഷ്യം വഹിക്കൽ...",
                            "type": "hadith",
                            "info": [
                                {
                                    "slug": "sahih-bukhari",
                                    "number": 8
                                }
                            ]
                        }
                    ]
                }
            ]
        },
        {
            "title": "ഏകദൈവ വിശ്വാസം (തൗഹീദ്) - ശഹാദത്തിൻ്റെ ഒന്നാം ഭാഗം",
            "desc": "",
            "active": false,
            "points": [
                {
                    "title": "തൗഹീദ് (ഏകത്വം)",
                    "desc": [
                        "അല്ലാഹുവിനെ മാത്രം ആരാധിക്കുകയും അവനിൽ യാതൊന്നിനെയും പങ്കുചേർക്കാതിരിക്കുകയും ചെയ്യുക.",
                        "അല്ലാഹു ഏകനാണ്. അവന് തുല്യനായി ആരുമില്ല. അവനാണ് ആരാധനക്ക് അർഹൻ. നമസ്കാരം, പ്രാർത്ഥന, നേർച്ച എന്നിവയെല്ലാം അവനുവേണ്ടി മാത്രമായിരിക്കണം."
                    ],
                    "ref": [
                        {
                            "title": "പറയുക: അവൻ അല്ലാഹുവാണ്, ഏകനാണ്. അല്ലാഹു ഏവർക്കും ആശ്രയമായിട്ടുള്ളവനാണ്. അവൻ (ആരുടെയും സന്തതിയായി) ജനിച്ചിട്ടില്ല. (ആരെയും) ജനിപ്പിച്ചിട്ടുമില്ല. അവന് തുല്യനായി ആരും തന്നെയില്ല.",
                            "type": "quran",
                            "info": [
                                {
                                    "slug": 112,
                                    "number": 1
                                },
                                {
                                    "slug": 112,
                                    "number": 4
                                }
                            ]
                        }
                    ]
                },
                {
                    "title": "ശിർക്ക് (ബഹുദൈവത്വം) ഒഴിവാക്കൽ",
                    "desc": [
                        "സ്രഷ്ടാവിലോ, അവകാശങ്ങളിലോ, ആരാധനയിലോ അല്ലാഹുവിനൊപ്പം മറ്റൊന്നിനെയും പങ്കുചേർക്കുന്നത് ഇസ്ലാം കർശനമായി വിലക്കുന്നു. ഇത് ഏറ്റവും വലിയ പാപമാണ്."
                    ],
                    "ref": [
                        {
                            "title": "തീര്‍ച്ചയായും അല്ലാഹു തന്നോട്‌ പങ്കുചേര്‍ക്കപ്പെടുന്നത്‌ പൊറുക്കുകയില്ല. അതൊഴിച്ചുള്ളതെല്ലാം അവന്‍ ഉദ്ദേശിക്കുന്നവര്‍ക്ക്‌ അവന്‍ പൊറുത്തുകൊടുക്കുന്നതാണ്‌.",
                            "type": "quran",
                            "info": [
                                {
                                    "slug": 4,
                                    "number": 48
                                }
                            ]
                        }
                    ]
                }
            ]
        },
        {
            "title": "ശുദ്ധിയാകാനുള്ള കുളി (ഗുസ്ൽ)",
            "desc": "",
            "active": false,
            "points": [
                {
                    "title": "കുളി നിർബന്ധമാകൽ",
                    "desc": [
                        "ഇസ്‌ലാമിലേക്ക് പ്രവേശിക്കുമ്പോൾ ശരീരത്തെ പൂർണ്ണമായി ശുദ്ധീകരിക്കുന്നതിനായി കുളി നിർബന്ധമാണ്."
                    ],
                    "ref": [
                        {
                            "title": "ഖൈസ് ഇബ്ൻ ആസിം (റ) ഇസ്‌ലാം സ്വീകരിച്ചപ്പോൾ നബി ﷺ അദ്ദേഹത്തോട് വെള്ളവും ഇലകളും ഉപയോഗിച്ച് കുളിക്കാൻ കൽപ്പിച്ചു.",
                            "type": "hadith",
                            "info": [
                                {
                                    "slug": "abu-dawood",
                                    "number": 355
                                }
                            ]
                        }
                    ]
                },
                {
                    "title": "കുളിയുടെ നിർബന്ധ ഘടകങ്ങൾ (ചുരുക്കത്തിൽ)",
                    "desc": [],
                    "list": [
                        "വലിയ അശുദ്ധിയിൽ നിന്ന് ശുദ്ധിയാകാൻ കുളിക്കുന്നു എന്ന് ഹൃദയത്തിൽ നിയ്യത്ത് (ഉദ്ദേശ്യം) കരുതുക.",
                        "ശരീരം മുഴുവൻ ഒരു ഭാഗം പോലും നനയാതെ ബാക്കിയാക്കാതെ, വെള്ളം കൊണ്ട് കഴുകുക. (വായിലും മൂക്കിലും വെള്ളം എത്തിക്കണം)."
                    ],
                    "ref": [
                        {
                            "title": "നിങ്ങള്‍ ജനാബത്ത് (വലിയ അശുദ്ധി) ബാധിച്ചവരായാല്‍ നിങ്ങള്‍ (കുളിച്ച്‌) ശുദ്ധിയാകുക.",
                            "type": "quran",
                            "info": [
                                {
                                    "slug": 5,
                                    "number": 6
                                }
                            ]
                        }
                    ]
                }
            ]
        },
        {
            "title": "അനുബന്ധ വിഷയം: നമസ്കാരം (സ്വലാത്ത്)",
            "desc": "",
            "active": false,
            "points": [
                {
                    "title": "നമസ്കാരത്തിൻ്റെ പ്രാധാന്യം",
                    "desc": [
                        "ശഹാദത്തിന് ശേഷം ഒരു മുസ്ലിമിന് നിർബന്ധമായ ഏറ്റവും പ്രധാനപ്പെട്ട ആരാധനയാണ് ദിവസവും അഞ്ച് നേരമുള്ള നമസ്കാരം.",
                        "ഇസ്‌ലാമിലെ രണ്ടാമത്തെ സ്തംഭമാണ് നമസ്കാരം. അത് വിശ്വാസിയെയും അവിശ്വാസിയെയും വേർതിരിക്കുന്ന അടയാളമാണ്."
                    ],
                    "ref": [
                        {
                            "title": "നമുക്കും അവർക്കുമിടയിലുള്ള ഉടമ്പടി നമസ്‌കാരമാണ്. ആരെങ്കിലും അത് ഉപേക്ഷിച്ചാൽ അവൻ അവിശ്വസിച്ചു.",
                            "type": "hadith",
                            "info": [
                                {
                                    "slug": "al-tirmidhi",
                                    "number": 2621
                                }
                            ]
                        }
                    ]
                }
            ]
        }
    ]
}
